{
  "$schema": "https://gist.githubusercontent.com/estruyf/d5696a00569fa67d14e83a965873e51c/raw/a3cfafa01d6d24bf89316ef372ba28ecd44e75ba/homebridge.schema.json",
  "pluginAlias": "presence-switch",
  "pluginType": "accessory",
  "singular": false,
  "headerDisplay": "Microsoft Graph Presence Switch",
  "footerDisplay": "Plugin which allows you retrieve your presence via the Microsoft Graph and call your busy light API.",
  "schema": {
    "$schema": "http://json-schema.org/draft-07/schema",
    "type": "object",
    "required": [
      "name",
      "appId"
    ],
    "properties": {
      "name": {
        "title": "Name",
        "type": "string",
        "default": "Presence Indicator"
      },
      "appId": {
        "title": "Azure AD application ID",
        "description": "The GUID of the Azure AD app.",
        "type": "string",
        "default": ""
      },
      "interval": {
        "title": "Interval",
        "description": "Polling interval.",
        "type": "integer",
        "default": 1
      },
      "setColorApi": {
        "title": "Set color API",
        "description": "API to set the color",
        "type": "string"
      },
      "offApi": {
        "title": "Off API",
        "description": "API to turn off your device",
        "type": "string"
      },
      "onApi": {
        "title": "On API",
        "description": "API to turn on your device",
        "type": "string"
      },
      "startTime": {
        "title": "Start time",
        "description": "Define the time when you start your working day (ex: 8:30).",
        "type": "string",
        "default": ""
      },
      "endTime": {
        "title": "End time",
        "description": "Define the time when you end your working day (ex: 18:00).",
        "type": "string",
        "default": ""
      },
      "weekend": {
        "title": "Weekend checks",
        "description": "Do you want to check in the weekends",
        "type": "boolean",
        "default": false
      },
      "statusColors": {
        "title": "Status color",
        "description": "Define the color values for the following states: 'available', 'busy', 'away' and 'do not disturb'.",
        "type": "object",
        "default": {},
        "properties": {
          "available": {
            "type": "object",
            "title": "Available",
            "description": "The color for when you are available.",
            "default": {},
            "required": [
              "red",
              "green",
              "blue"
            ],
            "properties": {
              "red": {
                "type": "integer",
                "title": "Red",
                "description": "Value between: 0 - 255.",
                "default": 0
              },
              "green": {
                "type": "integer",
                "title": "Green",
                "description": "Value between: 0 - 255.",
                "default": 144
              },
              "blue": {
                "type": "integer",
                "title": "Blue",
                "description": "Value between: 0 - 255.",
                "default": 0
              }
            }
          },
          "away": {
            "type": "object",
            "title": "Away",
            "description": "The color for when you are away.",
            "default": {},
            "required": [
              "red",
              "green",
              "blue"
            ],
            "properties": {
              "red": {
                "type": "integer",
                "title": "Red",
                "description": "Value between: 0 - 255.",
                "default": 255
              },
              "green": {
                "type": "integer",
                "title": "Green",
                "description": "Value between: 0 - 255.",
                "default": 191
              },
              "blue": {
                "type": "integer",
                "title": "Blue",
                "description": "Value between: 0 - 255.",
                "default": 0
              }
            }
          },
          "busy": {
            "type": "object",
            "title": "Busy",
            "description": "The color for when you are busy.",
            "default": {},
            "required": [
              "red",
              "green",
              "blue"
            ],
            "properties": {
              "red": {
                "type": "integer",
                "title": "Red",
                "description": "Value between: 0 - 255.",
                "default": 179
              },
              "green": {
                "type": "integer",
                "title": "Green",
                "description": "Value between: 0 - 255.",
                "default": 0
              },
              "blue": {
                "type": "integer",
                "title": "Blue",
                "description": "Value between: 0 - 255.",
                "default": 0
              }
            }
          },
          "donotdisturb": {
            "type": "object",
            "title": "Do Not Disturb",
            "description": "The color for when you are in do not disturb mode.",
            "default": {},
            "required": [
              "red",
              "green",
              "blue"
            ],
            "properties": {
              "red": {
                "type": "integer",
                "title": "Red",
                "description": "Value between: 0 - 255.",
                "default": 149
              },
              "green": {
                "type": "integer",
                "title": "Green",
                "description": "Value between: 0 - 255.",
                "default": 0
              },
              "blue": {
                "type": "integer",
                "title": "Blue",
                "description": "Value between: 0 - 255.",
                "default": 0
              }
            }
          }
        }
      },
      "lightType": {
        "title": "Light type",
        "description": "Define the type of light you want to show (not yet supported).",
        "type": "string",
        "default": "switch",
        "oneOf": [
          {
            "title": "default",
            "enum": [ "" ]
          },
          {
            "title": "Always on",
            "enum": [ "on" ]
          },
          {
            "title": "Blink",
            "enum": [ "blink" ]
          },
          {
            "title": "Hearthbeat",
            "enum": [ "hearthbeat" ]
          }
        ]
      },
      "debug": {
        "title": "Debug",
        "type": "boolean",
        "default": false
      }
    }
  },
    "layout":
    [
        {
            "items":
            [
                "name",
                "appId",
                "interval",
                "startTime",
                "endTime",
                "weekend"
            ]
        },
        {
            "type": "fieldset",
            "title": "Light Details",
            "description": "Expand to enter light API and colour details",
            "expandable": true,
            "items":
            [
                "setColorApi",
                "onApi",
                "offApi",
                "lightType"
            ]
        },
        {
            "key": "statusColors",
            "expandable": true,
            "title": "Status Colors",
            "description": "Expand to enter status color details",
            "type": "array",
            "items":
            [
                {
                    "type": "fieldset",
                    "items":
                    [
                        "statusColors",
                        "statusColors.available",
                        "statusColors.available.red",
                        "statusColors.available.green",
                        "statusColors.available.blue",
                        "statusColors.busy",
                        "statusColors.busy.red",
                        "statusColors.busy.green",
                        "statusColors.busy.blue",
                        "statusColors.away",
                        "statusColors.away.red",
                        "statusColors.away.green",
                        "statusColors.away.blue",
                        "statusColors.donotdisturb",
                        "statusColors.donotdisturb.red",
                        "statusColors.donotdisturb.green",
                        "statusColors.donotdisturb.blue"
                    ]
                }
            ]
        }
    ]
}
